etna/__init__.py
etna/analysis/__init__.py
etna/analysis/decomposition/__init__.py
etna/analysis/decomposition/plots.py
etna/analysis/decomposition/search.py
etna/analysis/decomposition/utils.py
etna/analysis/eda/__init__.py
etna/analysis/eda/plots.py
etna/analysis/eda/utils.py
etna/analysis/feature_relevance/__init__.py
etna/analysis/feature_relevance/plots.py
etna/analysis/feature_relevance/relevance.py
etna/analysis/feature_relevance/relevance_table.py
etna/analysis/feature_relevance/utils.py
etna/analysis/feature_selection/__init__.py
etna/analysis/feature_selection/mrmr_selection.py
etna/analysis/forecast/__init__.py
etna/analysis/forecast/plots.py
etna/analysis/forecast/utils.py
etna/analysis/outliers/__init__.py
etna/analysis/outliers/density_outliers.py
etna/analysis/outliers/hist_outliers.py
etna/analysis/outliers/isolation_forest_outliers.py
etna/analysis/outliers/median_outliers.py
etna/analysis/outliers/plots.py
etna/analysis/outliers/prediction_interval_outliers.py
etna/analysis/outliers/rolling_statistics.py
etna/analysis/utils.py
etna/auto/__init__.py
etna/auto/auto.py
etna/auto/optuna/__init__.py
etna/auto/optuna/config_sampler.py
etna/auto/optuna/wrapper.py
etna/auto/pool/__init__.py
etna/auto/pool/generator.py
etna/auto/pool/templates.py
etna/auto/pool/utils.py
etna/auto/runner/__init__.py
etna/auto/runner/base.py
etna/auto/runner/local.py
etna/auto/runner/utils.py
etna/auto/utils.py
etna/clustering/__init__.py
etna/clustering/base.py
etna/clustering/distances/__init__.py
etna/clustering/distances/base.py
etna/clustering/distances/distance_matrix.py
etna/clustering/distances/dtw_distance.py
etna/clustering/distances/euclidean_distance.py
etna/clustering/hierarchical/__init__.py
etna/clustering/hierarchical/base.py
etna/clustering/hierarchical/dtw_clustering.py
etna/clustering/hierarchical/euclidean_clustering.py
etna/commands/__init__.py
etna/commands/__main__.py
etna/commands/backtest_command.py
etna/commands/forecast_command.py
etna-3.0.0.dist-info/LICENSE
etna-3.0.0.dist-info/METADATA
etna-3.0.0.dist-info/WHEEL
etna-3.0.0.dist-info/entry_points.txt
etna-3.0.0.dist-info/RECORD
