Metadata-Version: 2.1
Name: etna
Version: 3.0.0
Summary: ETNA is the first python open source framework of T-Bank AI Center. It is designed to make working with time series simple, productive, and fun.
Home-page: https://github.com/etna-team/etna
License: Apache-2.0
Author: Andrey Alekseev
Author-email: ilekseev@gmail.com
Requires-Python: >=3.10.0,<3.13.0
Classifier: Development Status :: 5 - Production/Stable
Classifier: Intended Audience :: Developers
Classifier: Intended Audience :: Education
Classifier: Intended Audience :: Science/Research
Classifier: License :: OSI Approved :: Apache Software License
Classifier: Operating System :: MacOS
Classifier: Operating System :: Microsoft :: Windows
Classifier: Operating System :: Unix
Classifier: Programming Language :: Python :: 3
Classifier: Programming Language :: Python :: 3.10
Classifier: Programming Language :: Python :: 3.11
Classifier: Programming Language :: Python :: 3.12
Classifier: Topic :: Scientific/Engineering :: Artificial Intelligence
Classifier: Topic :: Software Development :: Libraries :: Python Modules
Provides-Extra: all
Provides-Extra: all-dev
Provides-Extra: auto
Provides-Extra: chronos
Provides-Extra: classification
Provides-Extra: clearml
Provides-Extra: docs
Provides-Extra: jupyter
Provides-Extra: prophet
Provides-Extra: release
Provides-Extra: statsforecast
Provides-Extra: style
Provides-Extra: tests
Provides-Extra: timesfm
Provides-Extra: torch
Provides-Extra: wandb
Requires-Dist: Bottleneck (>=1.3.4,<2.0.0)
Requires-Dist: Deprecated (==1.2.13)
Requires-Dist: GitPython (>=3.1.20,<4.0.0) ; extra == "docs" or extra == "all-dev"
Requires-Dist: Sphinx (>=6.2,<7.0) ; extra == "docs" or extra == "all-dev"
Requires-Dist: accelerate (>=1,<2) ; extra == "chronos" or extra == "all" or extra == "all-dev"
Requires-Dist: black[jupyter] (>=24.0,<25.0) ; extra == "jupyter" or extra == "style" or extra == "all-dev"
Requires-Dist: boto3 (>=1.5,<2.0)
Requires-Dist: botocore
Requires-Dist: catboost (>=1,<2)
Requires-Dist: clearml (>=1.15,<2.0) ; extra == "clearml" or extra == "all" or extra == "all-dev"
Requires-Dist: click (>=8.0.1,<8.1) ; extra == "release" or extra == "all-dev" or extra == "all-dev"
Requires-Dist: codespell (>=2.0.0,<3.0.0) ; extra == "style" or extra == "all-dev"
Requires-Dist: dill (>=0.3.4,<0.4.0)
Requires-Dist: einops ; extra == "torch" or extra == "all" or extra == "all-dev"
Requires-Dist: flake8 (>=3.9.2,<4.0.0) ; extra == "style" or extra == "all-dev"
Requires-Dist: flake8-bugbear (>=22.4.25,<23.0.0) ; extra == "style" or extra == "all-dev"
Requires-Dist: flake8-comprehensions (>=3.9.0,<4.0.0) ; extra == "style" or extra == "all-dev"
Requires-Dist: flake8-docstrings (>=1.6.0,<2.0.0) ; extra == "style" or extra == "all-dev"
Requires-Dist: holidays (>=0.40)
Requires-Dist: huggingface-hub (>=0.23) ; extra == "chronos" or extra == "timesfm" or extra == "all" or extra == "all-dev"
Requires-Dist: hydra-slayer (>=0.5)
Requires-Dist: hydra_slayer
Requires-Dist: ipywidgets (>=7.6.5,<8.0.0) ; extra == "jupyter" or extra == "all-dev"
Requires-Dist: isort (>=5.8.0,<6.0.0) ; extra == "style" or extra == "all-dev"
Requires-Dist: jax (>0.4.28,<1) ; extra == "timesfm" or extra == "all" or extra == "all-dev"
Requires-Dist: jaxlib (>0.4.25,<1) ; extra == "timesfm" or extra == "all" or extra == "all-dev"
Requires-Dist: joblib
Requires-Dist: jupyter ; extra == "docs" or extra == "jupyter" or extra == "all-dev"
Requires-Dist: lightning ; extra == "torch" or extra == "all" or extra == "all-dev"
Requires-Dist: loguru (>=0.7)
Requires-Dist: matplotlib
Requires-Dist: mypy (>=0.950,<2) ; extra == "style" or extra == "all-dev"
Requires-Dist: myst-parser (>=1.0,<2.0) ; extra == "docs" or extra == "all-dev"
Requires-Dist: nbconvert ; extra == "jupyter" or extra == "all-dev"
Requires-Dist: nbqa[isort] (>=1.7.0,<2.0.0) ; extra == "style" or extra == "all-dev"
Requires-Dist: nbsphinx (>=0.9.0,<0.10.0) ; extra == "docs" or extra == "all-dev"
Requires-Dist: numba (>=0.53.1)
Requires-Dist: numpy (<2)
Requires-Dist: omegaconf (>=2.1.1,<3.0.0)
Requires-Dist: optuna (>=4,<5) ; extra == "auto" or extra == "all" or extra == "all-dev"
Requires-Dist: pandas (>=2.0.0,<3.0.0)
Requires-Dist: pep8-naming (>=0.12.1,<0.13.0) ; extra == "style" or extra == "all-dev"
Requires-Dist: plotly (<6)
Requires-Dist: pmdarima (>=2.0.4)
Requires-Dist: prophet (>=1.0,<2.0) ; extra == "prophet" or extra == "all" or extra == "all-dev"
Requires-Dist: pydata-sphinx-theme (>=0.13.3,<0.14.0) ; extra == "docs" or extra == "all-dev"
Requires-Dist: pytest (>=7.3,<8.0) ; extra == "tests" or extra == "all-dev"
Requires-Dist: pytest-cov (>=4.0,<5.0) ; extra == "tests" or extra == "all-dev"
Requires-Dist: pytest-shard (>=0.1.2,<0.2.0) ; extra == "tests" or extra == "all-dev"
Requires-Dist: pyts (>=0.12.0,<0.13.0) ; extra == "classification" or extra == "all" or extra == "all-dev"
Requires-Dist: ruptures (>=1.1.5,<2.0.0)
Requires-Dist: scikit-learn (>=1.4,<2)
Requires-Dist: scipy (>=1.12)
Requires-Dist: seaborn (>=0.11.1,<1)
Requires-Dist: semver (>=2.13.0,<3.0.0) ; extra == "release" or extra == "all-dev" or extra == "all-dev"
Requires-Dist: sphinx-design (>=0.5.0,<0.6.0) ; extra == "docs" or extra == "all-dev"
Requires-Dist: sphinx-mathjax-offline (>=0.0.2,<0.0.3) ; extra == "docs" or extra == "all-dev"
Requires-Dist: statsforecast (>=2,<3) ; extra == "statsforecast" or extra == "all" or extra == "all-dev"
Requires-Dist: statsmodels (>=0.14,<0.15)
Requires-Dist: tbats (>=1.1.0,<2.0.0)
Requires-Dist: tensorboard (>=2.12.0,<3.0.0) ; extra == "clearml" or extra == "all" or extra == "all-dev"
Requires-Dist: toml (>=0.10.2,<0.11.0)
Requires-Dist: torch (>=2,<3) ; extra == "torch" or extra == "chronos" or extra == "timesfm" or extra == "all" or extra == "all-dev"
Requires-Dist: transformers (>=4.42,<5) ; extra == "chronos" or extra == "all" or extra == "all-dev"
Requires-Dist: tsfresh (>=0.21.0,<0.22.0) ; extra == "classification" or extra == "all" or extra == "all-dev"
Requires-Dist: typer (>=0.12)
Requires-Dist: types-Deprecated (==1.2.9)
Requires-Dist: types-PyYAML (>=6.0.0,<7.0.0) ; extra == "style" or extra == "all-dev"
Requires-Dist: types-setuptools (>=65.7.0,<66.0.0) ; extra == "style" or extra == "all-dev"
Requires-Dist: typing_extensions (>=4.1.0,<5.0.0)
Requires-Dist: utilsforecast (>=0.1.10,<1) ; extra == "timesfm" or extra == "all" or extra == "all-dev"
Requires-Dist: wandb (>=0.16) ; extra == "wandb" or extra == "all" or extra == "all-dev"
Project-URL: Repository, https://github.com/etna-team/etna
